{
  "main": {
    "id": "0423e45cdfd6d4a2",
    "type": "split",
    "children": [
      {
        "id": "ea6e00efc6370a59",
        "type": "tabs",
        "children": [
          {
            "id": "56ea5e91bb166c0a",
            "type": "leaf",
            "state": {
              "type": "markdown",
              "state": {
                "file": "notes/MAD/0305.md",
                "mode": "source",
                "source": false
              }
            }
          }
        ]
      }
    ],
    "direction": "vertical"
  },
  "left": {
    "id": "b55f559b6c7b5274",
    "type": "split",
    "children": [
      {
        "id": "1f901cb0c7fedb84",
        "type": "tabs",
        "children": [
          {
            "id": "73ea793750b2f734",
            "type": "leaf",
            "state": {
              "type": "file-explorer",
              "state": {
                "sortOrder": "alphabetical"
              }
            }
          },
          {
            "id": "2c54424a9dcc8d9d",
            "type": "leaf",
            "state": {
              "type": "search",
              "state": {
                "query": "",
                "matchingCase": false,
                "explainSearch": false,
                "collapseAll": false,
                "extraContext": false,
                "sortOrder": "alphabetical"
              }
            }
          },
          {
            "id": "7f8f94f850a6d199",
            "type": "leaf",
            "state": {
              "type": "bookmarks",
              "state": {}
            }
          }
        ]
      }
    ],
    "direction": "horizontal",
    "width": 200
  },
  "right": {
    "id": "8a8dc465d0d57602",
    "type": "split",
    "children": [
      {
        "id": "a035d107d5ca0b43",
        "type": "tabs",
        "children": [
          {
            "id": "be029e3c9701bede",
            "type": "leaf",
            "state": {
              "type": "backlink",
              "state": {
                "file": "notes/MAD/0305.md",
                "collapseAll": false,
                "extraContext": false,
                "sortOrder": "alphabetical",
                "showSearch": false,
                "searchQuery": "",
                "backlinkCollapsed": false,
                "unlinkedCollapsed": true
              }
            }
          },
          {
            "id": "df4fc172d65fd5f2",
            "type": "leaf",
            "state": {
              "type": "outgoing-link",
              "state": {
                "file": "notes/MAD/0305.md",
                "linksCollapsed": false,
                "unlinkedCollapsed": true
              }
            }
          },
          {
            "id": "50dec1b0c94f28df",
            "type": "leaf",
            "state": {
              "type": "tag",
              "state": {
                "sortOrder": "frequency",
                "useHierarchy": true
              }
            }
          },
          {
            "id": "bb81d2f9faf2b1c7",
            "type": "leaf",
            "state": {
              "type": "outline",
              "state": {
                "file": "notes/MAD/0305.md"
              }
            }
          }
        ]
      }
    ],
    "direction": "horizontal",
    "width": 300,
    "collapsed": true
  },
  "left-ribbon": {
    "hiddenItems": {
      "switcher:Open quick switcher": false,
      "graph:Open graph view": false,
      "canvas:Create new canvas": false,
      "templates:Insert template": false,
      "command-palette:Open command palette": false,
      "obsidian-excalidraw-plugin:Create new drawing": false
    }
  },
  "active": "56ea5e91bb166c0a",
  "lastOpenFiles": [
    "notes/EDS/0226.md",
    "notes/MAD/0305.md",
    "notes/MAD",
    "notes/Untitled.md",
    "notes/EDS/Aula 2.md",
    "notes/NIPOMED.md",
    "ASAAS.md",
    "Linux.md",
    "Pasted image 20240226103523.png",
    "sc-2024-02-26T09-18-02.png",
    "sc-2024-02-26T09-13-56.png",
    "sc-2024-02-26T09-13-17.png",
    "sc-2024-02-26T09-08-09.png",
    "sc-2024-02-26T09-07-29.png",
    "sc-2024-02-26T08-48-23.png",
    "sc-2024-02-26T08-41-08.png",
    "Pasted image 20240226103553.png",
    "Pasted image 20240226095757.png",
    "notes/SEM02/C/3- Estruturas.md",
    "notes/SEM02/JAVA/1- Base.md",
    "notes/SEM02/JAVA/3- Modificador de acesso.md",
    "notes/SEM02/JAVA/4- 4 Pilares de DOO.md",
    "notes/SEM02/JAVA/5- Herança.md",
    "notes/SEM02/JAVA/FORMS/FORMS.md",
    "notes/EDS",
    "TODO.md",
    "notes/SEM02",
    "notes/SEM02/KT/BASICS.md",
    "notes/SEM02/KT",
    "PY/Pandas.md",
    "PY/Strings.md",
    "PY/Listas.md",
    "PY/Exception.md",
    "notes/SEM02/JS/10- Frontend.md",
    "notes/JS/Untitled.md",
    "notes/SEM02/JS/8- Aplicações Web.md",
    "notes/SEM02/JS/9- Backend.md",
    "notes/SEM02/JS/7- Operações Assíncronas.md",
    "notes/SEM02/JS/6- POO.md",
    "notes/SEM02/JS/5- Modularidade.md",
    "PY",
    "notes/SEM02/ARQ/Media",
    "notes/SEM02/JAVA/FORMS",
    "notes/SEM02/JS/Forms",
    "notes/SEM02/JAVA/Media",
    "notes/SEM02/BD/Media",
    "Untitled.canvas"
  ]
}